{
    "sweep_id": "00wf2w43",
    "summary": {
        "_wandb": {
            "runtime": 120
        },
        "val_std": 0.3,
        "test_std": 0.7,
        "val_mean": 81.6,
        "test_mean": 78.7,
        "_timestamp": 1705213293.214541,
        "_step": 0,
        "_runtime": 121.80400490760805,
        "val_loss": 0.703,
        "train_loss": 0.546
    },
    "config": {
        "lr": 0.01,
        "model": "chatgnn",
        "n_runs": 3,
        "dataset": "citeseer",
        "dropout": 0.5,
        "loglevel": "error",
        "layer_norm": false,
        "num_layers": 4,
        "save_model": true,
        "hidden_size": 64,
        "weight_decay": 0.0005,
        "post_transform": false,
        "initial_dropout": true
    }
}